airpt2/__init__.py
airpt2/airpt.py
airpt2-1.0.0.dist-info/METADATA
airpt2-1.0.0.dist-info/WHEEL
airpt2-1.0.0.dist-info/top_level.txt
airpt2-1.0.0.dist-info/RECORD
